S3RL/Optimize_prototypes.py
S3RL/__init__.py
S3RL/backbone.py
S3RL/model.py
S3RL/process_data.py
S3RL/tools.py
S3RL-0.1.1.dist-info/LICENSE
S3RL-0.1.1.dist-info/METADATA
S3RL-0.1.1.dist-info/WHEEL
S3RL-0.1.1.dist-info/top_level.txt
S3RL-0.1.1.dist-info/RECORD
