Metadata-Version: 2.1
Name: S3RL
Version: 0.1.1
Summary: S3RL: Separable Spatial Single-cell Transcriptome Representation Learning via Graph Transformer and Hyperspherical Prototype Clustering
Home-page: UNKNOWN
Author: Penglei Wang
Author-email: pengleiwangcn@gmail.com
License: UNKNOWN
Platform: UNKNOWN
License-File: LICENSE
